wsi_toolbox/__init__.py
wsi_toolbox/cli.py
wsi_toolbox/common.py
wsi_toolbox/models.py
wsi_toolbox/patch_reader.py
wsi_toolbox/watcher.py
wsi_toolbox/wsi_files.py
wsi_toolbox/app/__init__.py
wsi_toolbox/app/main.py
wsi_toolbox/app/ui/__init__.py
wsi_toolbox/app/ui/config.py
wsi_toolbox/app/ui/models.py
wsi_toolbox/app/ui/state.py
wsi_toolbox/app/ui/pages/__init__.py
wsi_toolbox/app/ui/pages/hdf5.py
wsi_toolbox/app/ui/pages/wsi.py
wsi_toolbox/commands/__init__.py
wsi_toolbox/commands/cache.py
wsi_toolbox/commands/clustering.py
wsi_toolbox/commands/data_loader.py
wsi_toolbox/commands/dzi.py
wsi_toolbox/commands/feature_extraction.py
wsi_toolbox/commands/pca.py
wsi_toolbox/commands/preview.py
wsi_toolbox/commands/show.py
wsi_toolbox/commands/umap_embedding.py
wsi_toolbox/utils/__init__.py
wsi_toolbox/utils/analysis.py
wsi_toolbox/utils/hdf5_paths.py
wsi_toolbox/utils/plot.py
wsi_toolbox/utils/progress.py
wsi_toolbox/utils/seed.py
wsi_toolbox/utils/st.py
wsi_toolbox/utils/white.py
wsi_toolbox-0.3.2.dist-info/METADATA
wsi_toolbox-0.3.2.dist-info/WHEEL
wsi_toolbox-0.3.2.dist-info/entry_points.txt
wsi_toolbox-0.3.2.dist-info/licenses/LICENSE
wsi_toolbox-0.3.2.dist-info/RECORD
