Metadata-Version: 2.4
Name: wsi-toolbox
Version: 0.3.2
Summary: A comprehensive toolkit for Whole Slide Image processing, feature extraction, and clustering analysis
Project-URL: Homepage, https://github.com/technoplasm/wsi-toolbox
Project-URL: Repository, https://github.com/technoplasm/wsi-toolbox
Project-URL: Documentation, https://github.com/technoplasm/wsi-toolbox/blob/master/README.md
Author-email: Ken Enda <ken@endaaman.com>
License: MIT License
License-File: LICENSE
Keywords: clustering,deep-learning,histopathology,pathology,wsi
Classifier: Development Status :: 4 - Beta
Classifier: Intended Audience :: Science/Research
Classifier: License :: OSI Approved :: MIT License
Classifier: Programming Language :: Python :: 3.11
Classifier: Topic :: Scientific/Engineering :: Medical Science Apps.
Requires-Python: ==3.12.*
Requires-Dist: h5py>=3.13.0
Requires-Dist: imagecodecs>=2024.12.30
Requires-Dist: joblib>=1.4.2
Requires-Dist: leidenalg>=0.10.2
Requires-Dist: matplotlib>=3.9.4
Requires-Dist: networkx>=3.3
Requires-Dist: numpy<2
Requires-Dist: opencv-python-headless>=4.11.0.86
Requires-Dist: openpyxl>=3.1.5
Requires-Dist: openslide-python>=1.4.1
Requires-Dist: pandas>=2.2.3
Requires-Dist: pillow>=11.0.0
Requires-Dist: pydantic-autocli>=0.2.0
Requires-Dist: pyqt6>=6.8.1
Requires-Dist: python-igraph>=0.11.8
Requires-Dist: rich>=14.0.0
Requires-Dist: scikit-learn>=1.6.1
Requires-Dist: seaborn>=0.13.2
Requires-Dist: streamlit-aggrid>=0.3.4.post3
Requires-Dist: streamlit-antd-components>=0.3.2
Requires-Dist: streamlit>=1.43.2
Requires-Dist: taskipy>=1.14.1
Requires-Dist: tifffile>=2025.2.18
Requires-Dist: timm>=0.9.16
Requires-Dist: torch>=2.5.1
Requires-Dist: torchvision>=0.20.1
Requires-Dist: umap-learn>=0.5.7
Requires-Dist: zarr>=3
Provides-Extra: build
Requires-Dist: packaging; extra == 'build'
Requires-Dist: setuptools; extra == 'build'
Requires-Dist: torch; extra == 'build'
Requires-Dist: wheel; extra == 'build'
Provides-Extra: compile
Requires-Dist: flash-attn; extra == 'compile'
